kidx_nlu/__init__.py
kidx_nlu/components.py
kidx_nlu/config.py
kidx_nlu/convert.py
kidx_nlu/data_router.py
kidx_nlu/evaluate.py
kidx_nlu/model.py
kidx_nlu/persistor.py
kidx_nlu/project.py
kidx_nlu/registry.py
kidx_nlu/run.py
kidx_nlu/server.py
kidx_nlu/test.py
kidx_nlu/train.py
kidx_nlu/version.py
kidx_nlu/classifiers/__init__.py
kidx_nlu/classifiers/embedding_bert_intent_classifier.py
kidx_nlu/classifiers/embedding_intent_classifier.py
kidx_nlu/classifiers/fastText_sentiment_classifier.py
kidx_nlu/classifiers/keyword_intent_classifier.py
kidx_nlu/classifiers/mitie_intent_classifier.py
kidx_nlu/classifiers/sklearn_intent_classifier.py
kidx_nlu/cli/__init__.py
kidx_nlu/cli/server.py
kidx_nlu/emulators/__init__.py
kidx_nlu/emulators/dialogflow.py
kidx_nlu/emulators/luis.py
kidx_nlu/emulators/wit.py
kidx_nlu/extractors/PyLTP_extractor.py
kidx_nlu/extractors/__init__.py
kidx_nlu/extractors/bilstm_crf_entity_extractor.py
kidx_nlu/extractors/crf_entity_extractor.py
kidx_nlu/extractors/duckling_http_extractor.py
kidx_nlu/extractors/entity_synonyms.py
kidx_nlu/extractors/jieba_pseg_extractor.py
kidx_nlu/extractors/mitie_entity_extractor.py
kidx_nlu/extractors/spacy_entity_extractor.py
kidx_nlu/featurizers/__init__.py
kidx_nlu/featurizers/bert_vectors_featurizer.py
kidx_nlu/featurizers/count_vectors_featurizer.py
kidx_nlu/featurizers/mitie_featurizer.py
kidx_nlu/featurizers/ngram_featurizer.py
kidx_nlu/featurizers/regex_featurizer.py
kidx_nlu/featurizers/spacy_featurizer.py
kidx_nlu/models/__init__.py
kidx_nlu/models/bilstm_model.py
kidx_nlu/models/lenet.py
kidx_nlu/tokenizers/__init__.py
kidx_nlu/tokenizers/jieba_tokenizer.py
kidx_nlu/tokenizers/mitie_tokenizer.py
kidx_nlu/tokenizers/pku_tokenizer.py
kidx_nlu/tokenizers/spacy_tokenizer.py
kidx_nlu/tokenizers/whitespace_tokenizer.py
kidx_nlu/training_data/__init__.py
kidx_nlu/training_data/loading.py
kidx_nlu/training_data/message.py
kidx_nlu-0.0.1a7.dist-info/LICENSE.txt
kidx_nlu-0.0.1a7.dist-info/METADATA
kidx_nlu-0.0.1a7.dist-info/RECORD
kidx_nlu-0.0.1a7.dist-info/WHEEL
kidx_nlu-0.0.1a7.dist-info/top_level.txt
