Metadata-Version: 2.1
Name: kidx-nlu
Version: 0.0.1a7
Summary: Kidx NLU a natural language parser for bots
Home-page: https://mykidx.com
Author: Kidx AI
Author-email: nlp@mykidx.com
Maintainer: Cicean Wang
Maintainer-email: nlp@mykidx.com
License: Apache 2.0
Download-URL: http://git.mykidx.com/nlp/kidx_nlu/-/archive/0.0.1a7/kidx_nlu-0.0.1a7-test.tar.gz
Project-URL: Bug Reports, http://redmine.mykidx.com/projects/kidx-nlu/issues
Project-URL: Source, http://git.mykidx.com/nlp/kidx_nlu
Keywords: nlp machine-learning machine-learning-library bot bots botkit kidx conversational-agents conversational-ai chatbotchatbot-framework bot-framework
Platform: UNKNOWN
Classifier: Development Status :: 4 - Beta
Classifier: Intended Audience :: Developers
Classifier: License :: OSI Approved :: Apache Software License
Classifier: Programming Language :: Python
Classifier: Programming Language :: Python :: 3.5
Classifier: Programming Language :: Python :: 3.6
Classifier: Topic :: Software Development :: Libraries
Provides-Extra: spacy
Provides-Extra: tensorflow
Provides-Extra: mitie
Provides-Extra: test
Requires-Dist: cloudpickle (~=0.6.1)
Requires-Dist: gevent (~=1.2)
Requires-Dist: klein (~=17.10)
Requires-Dist: boto3 (~=1.9.12)
Requires-Dist: packaging (~=18.0)
Requires-Dist: typing (~=3.6)
Requires-Dist: future (~=0.17.1)
Requires-Dist: tqdm (~=4.19)
Requires-Dist: requests (~=2.20)
Requires-Dist: jsonschema (~=2.6)
Requires-Dist: matplotlib (~=2.0)
Requires-Dist: numpy (~=1.16.2)
Requires-Dist: simplejson (~=3.13)
Requires-Dist: ruamel.yaml (~=0.15.7)
Requires-Dist: coloredlogs (~=10.0)
Requires-Dist: scikit-learn (~=0.20.2)
Requires-Dist: pyltp (~=0.1.9.1)
Requires-Dist: jieba (~=0.39)
Requires-Dist: sklearn-crfsuite (~=0.3.6)
Requires-Dist: scipy (~=1.2.1)
Requires-Dist: bert-serving-client (~=1.8.9)
Requires-Dist: pkuseg (~=0.0.21)
Provides-Extra: mitie
Requires-Dist: mitie; extra == 'mitie'
Provides-Extra: spacy
Requires-Dist: spacy (<=2.1.3,>2.0); extra == 'spacy'
Provides-Extra: tensorflow
Requires-Dist: tensorflow (~=1.12.0); extra == 'tensorflow'
Requires-Dist: keras-applications (==1.0.6); extra == 'tensorflow'
Requires-Dist: keras-preprocessing (==1.0.5); extra == 'tensorflow'
Provides-Extra: test
Requires-Dist: pytest (~=3.3); extra == 'test'
Requires-Dist: pytest-pycodestyle (~=1.4); extra == 'test'
Requires-Dist: pytest-cov (~=2.5); extra == 'test'
Requires-Dist: pytest-twisted (<1.6); extra == 'test'
Requires-Dist: treq (~=17.8); extra == 'test'
Requires-Dist: responses (~=0.9.0); extra == 'test'
Requires-Dist: httpretty (~=0.9.0); extra == 'test'
